{
  "current": {
    "customer_layout": "customer_area",
    "logo_width": "754px",
    "logo_height": "163px",
    "h_font_family": "BebasRegular, Anton, 'Arial Black', 'Arial Bold', Gadget, sans-serif",
    "p_font_family": "'Open Sans Condensed', Univers, Calibri, 'Gill Sans', 'Gill Sans MT', 'Myriad Pro', Myriad, 'DejaVu Sans Condensed', 'Liberation Sans', 'Nimbus Sans L', Tahoma, Geneva, 'Helvetica Neue', Helvetica, Arial, sans-serif;",
    "font_size": "16px",
    "line_height": "1.25",
    "color": "#333",
    "selection_bgcolor": "#dddddd",
    "link_color": "#000000",
    "link_hovercolor": "#333333",
    "button_color": "#00e00e",
    "button_font_color": "#ffffff",
    "button_hovercolor": "#551a8b",
    "button_font_hovercolor": "#551a8b",
    "button2_color": "#551a8b",
    "button2_font_color": "#551a8b",
    "button2_hovercolor": "#00e00e",
    "button2_font_hovercolor": "#ffffff",
    "border_color": "#000000",
    "slide_order": "3,1,2",
    "slide_1_link": "\/collections\/all",
    "slide_1_alt": "",
    "slide_2_link": "\/collections\/all",
    "slide_2_alt": "",
    "header_font_size": "38px",
    "vcard_url": "http:\/\/url.com\/",
    "vcard_org": "url.com",
    "vcard_email": "\/pages\/contact-us",
    "vcard_display_email": "email@url.com",
    "vcard_street_address": "Some Street",
    "vcard_city": "Someplace",
    "vcard_region": "Somewhere",
    "vcard_postal_code": "123",
    "vard_country_name": "Wherever",
    "vcard_tel": "(123)456-7890",
    "checkout_banner_background_color": "#fff",
    "checkout_accent_color": "#2a9dcc",
    "checkout_button_color": "#2a9dcc",
    "checkout_call_to_action_color": "#8fc243",
    "checkout_logo": "",
    "use_logo": false,
    "checkout_use_header_image": false,
    "slide1_alt": "",
    "slide1_link": "",
    "slide2_alt": "",
    "slide2_link": "",
    "slide3_alt": "",
    "slide3_link": "",
    "slide4_alt": "",
    "slide4_link": "",
    "slide5_alt": "",
    "slide5_link": "",
    "slide6_alt": "",
    "slide6_link": "",
    "slide7_alt": "",
    "slide7_link": "",
    "slide8_alt": "",
    "slide8_link": "",
    "slide9_alt": "",
    "slide9_link": "",
    "slide10_alt": "",
    "slide10_link": "",
    "slide_number": "2",
    "slide_effect": "fade",
    "box1_alt": "",
    "box1_link": "",
    "box2_alt": "",
    "box2_link": "",
    "box3_alt": "",
    "box3_link": "",
    "box4_alt": "",
    "box4_link": "",
    "front_box_total": "3"
  },
  "presets": {
    "Grind": {
      "customer_layout": "customer_area",
      "header_font_size": "38px",
      "logo_width": "754px",
      "logo_height": "163px",
      "font_size": "16px",
      "line_height": "1.25",
      "color": "#333",
      "selection_bgcolor": "#dddddd",
      "link_color": "#000000",
      "link_hovercolor": "#333333",
      "slide1_alt": "",
      "slide1_link": "",
      "slide2_alt": "",
      "slide2_link": "",
      "slide3_alt": "",
      "slide3_link": "",
      "slide4_alt": "",
      "slide4_link": "",
      "slide5_alt": "",
      "slide5_link": "",
      "slide6_alt": "",
      "slide6_link": "",
      "slide7_alt": "",
      "slide7_link": "",
      "slide8_alt": "",
      "slide8_link": "",
      "slide9_alt": "",
      "slide9_link": "",
      "slide10_alt": "",
      "slide10_link": "",
      "box1_alt": "",
      "box1_link": "",
      "box2_alt": "",
      "box2_link": "",
      "box3_alt": "",
      "box3_link": "",
      "box4_alt": "",
      "box4_link": "",
      "vcard_url": "http:\/\/url.com\/",
      "vcard_org": "url.com",
      "vcard_email": "\/pages\/contact-us",
      "vcard_display_email": "email@url.com",
      "vcard_street_address": "Some Street",
      "vcard_city": "Someplace",
      "vcard_region": "Somewhere",
      "vcard_postal_code": "123",
      "vard_country_name": "Wherever",
      "vcard_tel": "(123)456-7890",
      "h_font_family": "'BebasRegular', 'Arial Black', 'Arial Bold', Gadget, sans-serif",
      "p_font_family": "'Open Sans Condensed', Univers, Calibri, 'Gill Sans', 'Gill Sans MT', 'Myriad Pro', Myriad, 'DejaVu Sans Condensed', 'Liberation Sans', 'Nimbus Sans L', Tahoma, Geneva, 'Helvetica Neue', Helvetica, Arial, sans-serif;",
      "slide_number": "1",
      "slide_effect": "slide",
      "front_box_total": "3",
      "use_logo": false
    }
  }
}